[{"fp": "COO", "from": "Cotonou", "ap": "LFW", "country": "Togo", "al": "Royal Air Maroc", "to": "Lome", "Flights": 2.2}, {"fp": "COO", "from": "Cotonou", "ap": "LFW", "country": "Togo", "al": "Total", "to": "Lome", "Flights": 0}, {"fp": "COO", "from": "Cotonou", "ap": "Total", "country": "Togo", "al": "Royal Air Maroc", "to": "Lome", "Flights": 0}, {"fp": "COO", "from": "Cotonou", "ap": "LFW", "country": "Total", "al": "Royal Air Maroc", "to": "Lome", "Flights": 0}, {"fp": "COO", "from": "Total", "ap": "LFW", "country": "Togo", "al": "Royal Air Maroc", "to": "Lome", "Flights": 0}, {"fp": "Total", "from": "Cotonou", "ap": "LFW", "country": "Togo", "al": "Royal Air Maroc", "to": "Lome", "Flights": 0}, {"fp": "COO", "from": "Cotonou", "ap": "LFW", "country": "Togo", "al": "Royal Air Maroc", "to": "Total", "Flights": 0}, {"fp": "COO", "from": "Cotonou", "ap": "LFW", "country": "Togo", "al": "ASKY", "to": "Lome", "Flights": 5.5}, {"fp": "COO", "from": "Cotonou", "ap": "LFW", "country": "Togo", "al": "Total", "to": "Lome", "Flights": 0}, {"fp": "COO", "from": "Cotonou", "ap": "Total", "country": "Togo", "al": "ASKY", "to": "Lome", "Flights": 0}, {"fp": "COO", "from": "Cotonou", "ap": "LFW", "country": "Total", "al": "ASKY", "to": "Lome", "Flights": 0}, {"fp": "COO", "from": "Total", "ap": "LFW", "country": "Togo", "al": "ASKY", "to": "Lome", "Flights": 0}, {"fp": "Total", "from": "Cotonou", "ap": "LFW", "country": "Togo", "al": "ASKY", "to": "Lome", "Flights": 0}, {"fp": "COO", "from": "Cotonou", "ap": "LFW", "country": "Togo", "al": "ASKY", "to": "Total", "Flights": 0}, {"fp": "COO", "from": "Cotonou", "ap": "LFW", "country": "Togo", "al": "Air Burkina", "to": "Lome", "Flights": 3.0}, {"fp": "COO", "from": "Cotonou", "ap": "LFW", "country": "Togo", "al": "Total", "to": "Lome", "Flights": 0}, {"fp": "COO", "from": "Cotonou", "ap": "Total", "country": "Togo", "al": "Air Burkina", "to": "Lome", "Flights": 0}, {"fp": "COO", "from": "Cotonou", "ap": "LFW", "country": "Total", "al": "Air Burkina", "to": "Lome", "Flights": 0}, {"fp": "COO", "from": "Total", "ap": "LFW", "country": "Togo", "al": "Air Burkina", "to": "Lome", "Flights": 0}, {"fp": "Total", "from": "Cotonou", "ap": "LFW", "country": "Togo", "al": "Air Burkina", "to": "Lome", "Flights": 0}, {"fp": "COO", "from": "Cotonou", "ap": "LFW", "country": "Togo", "al": "Air Burkina", "to": "Total", "Flights": 0}, {"fp": "COO", "from": "Cotonou", "ap": "LBV", "country": "Gabon", "al": "RwandAir", "to": "Libreville", "Flights": 5.0}, {"fp": "COO", "from": "Cotonou", "ap": "LBV", "country": "Gabon", "al": "Total", "to": "Libreville", "Flights": 0}, {"fp": "COO", "from": "Cotonou", "ap": "Total", "country": "Gabon", "al": "RwandAir", "to": "Libreville", "Flights": 0}, {"fp": "COO", "from": "Cotonou", "ap": "LBV", "country": "Total", "al": "RwandAir", "to": "Libreville", "Flights": 0}, {"fp": "COO", "from": "Total", "ap": "LBV", "country": "Gabon", "al": "RwandAir", "to": "Libreville", "Flights": 0}, {"fp": "Total", "from": "Cotonou", "ap": "LBV", "country": "Gabon", "al": "RwandAir", "to": "Libreville", "Flights": 0}, {"fp": "COO", "from": "Cotonou", "ap": "LBV", "country": "Gabon", "al": "RwandAir", "to": "Total", "Flights": 0}, {"fp": "COO", "from": "Cotonou", "ap": "LBV", "country": "Gabon", "al": "Air Cote d'Ivoire", "to": "Libreville", "Flights": 4.0}, {"fp": "COO", "from": "Cotonou", "ap": "LBV", "country": "Gabon", "al": "Total", "to": "Libreville", "Flights": 0}, {"fp": "COO", "from": "Cotonou", "ap": "Total", "country": "Gabon", "al": "Air Cote d'Ivoire", "to": "Libreville", "Flights": 0}, {"fp": "COO", "from": "Cotonou", "ap": "LBV", "country": "Total", "al": "Air Cote d'Ivoire", "to": "Libreville", "Flights": 0}, {"fp": "COO", "from": "Total", "ap": "LBV", "country": "Gabon", "al": "Air Cote d'Ivoire", "to": "Libreville", "Flights": 0}, {"fp": "Total", "from": "Cotonou", "ap": "LBV", "country": "Gabon", "al": "Air Cote d'Ivoire", "to": "Libreville", "Flights": 0}, {"fp": "COO", "from": "Cotonou", "ap": "LBV", "country": "Gabon", "al": "Air Cote d'Ivoire", "to": "Total", "Flights": 0}, {"fp": "COO", "from": "Cotonou", "ap": "LBV", "country": "Gabon", "al": "South African Airways", "to": "Libreville", "Flights": 3.0}, {"fp": "COO", "from": "Cotonou", "ap": "LBV", "country": "Gabon", "al": "Total", "to": "Libreville", "Flights": 0}, {"fp": "COO", "from": "Cotonou", "ap": "Total", "country": "Gabon", "al": "South African Airways", "to": "Libreville", "Flights": 0}, {"fp": "COO", "from": "Cotonou", "ap": "LBV", "country": "Total", "al": "South African Airways", "to": "Libreville", "Flights": 0}, {"fp": "COO", "from": "Total", "ap": "LBV", "country": "Gabon", "al": "South African Airways", "to": "Libreville", "Flights": 0}, {"fp": "Total", "from": "Cotonou", "ap": "LBV", "country": "Gabon", "al": "South African Airways", "to": "Libreville", "Flights": 0}, {"fp": "COO", "from": "Cotonou", "ap": "LBV", "country": "Gabon", "al": "South African Airways", "to": "Total", "Flights": 0}, {"fp": "COO", "from": "Cotonou", "ap": "LBV", "country": "Gabon", "al": "Trans Air Congo", "to": "Libreville", "Flights": 3.0}, {"fp": "COO", "from": "Cotonou", "ap": "LBV", "country": "Gabon", "al": "Total", "to": "Libreville", "Flights": 0}, {"fp": "COO", "from": "Cotonou", "ap": "Total", "country": "Gabon", "al": "Trans Air Congo", "to": "Libreville", "Flights": 0}, {"fp": "COO", "from": "Cotonou", "ap": "LBV", "country": "Total", "al": "Trans Air Congo", "to": "Libreville", "Flights": 0}, {"fp": "COO", "from": "Total", "ap": "LBV", "country": "Gabon", "al": "Trans Air Congo", "to": "Libreville", "Flights": 0}, {"fp": "Total", "from": "Cotonou", "ap": "LBV", "country": "Gabon", "al": "Trans Air Congo", "to": "Libreville", "Flights": 0}, {"fp": "COO", "from": "Cotonou", "ap": "LBV", "country": "Gabon", "al": "Trans Air Congo", "to": "Total", "Flights": 0}, {"fp": "COO", "from": "Cotonou", "ap": "LOS", "country": "Nigeria", "al": "Kenya Airways", "to": "Lagos", "Flights": 1.5}, {"fp": "COO", "from": "Cotonou", "ap": "LOS", "country": "Nigeria", "al": "Total", "to": "Lagos", "Flights": 0}, {"fp": "COO", "from": "Cotonou", "ap": "Total", "country": "Nigeria", "al": "Kenya Airways", "to": "Lagos", "Flights": 0}, {"fp": "COO", "from": "Cotonou", "ap": "LOS", "country": "Total", "al": "Kenya Airways", "to": "Lagos", "Flights": 0}, {"fp": "COO", "from": "Total", "ap": "LOS", "country": "Nigeria", "al": "Kenya Airways", "to": "Lagos", "Flights": 0}, {"fp": "Total", "from": "Cotonou", "ap": "LOS", "country": "Nigeria", "al": "Kenya Airways", "to": "Lagos", "Flights": 0}, {"fp": "COO", "from": "Cotonou", "ap": "LOS", "country": "Nigeria", "al": "Kenya Airways", "to": "Total", "Flights": 0}, {"fp": "COO", "from": "Cotonou", "ap": "LOS", "country": "Nigeria", "al": "Arik Air", "to": "Lagos", "Flights": 10.2}, {"fp": "COO", "from": "Cotonou", "ap": "LOS", "country": "Nigeria", "al": "Total", "to": "Lagos", "Flights": 0}, {"fp": "COO", "from": "Cotonou", "ap": "Total", "country": "Nigeria", "al": "Arik Air", "to": "Lagos", "Flights": 0}, {"fp": "COO", "from": "Cotonou", "ap": "LOS", "country": "Total", "al": "Arik Air", "to": "Lagos", "Flights": 0}, {"fp": "COO", "from": "Total", "ap": "LOS", "country": "Nigeria", "al": "Arik Air", "to": "Lagos", "Flights": 0}, {"fp": "Total", "from": "Cotonou", "ap": "LOS", "country": "Nigeria", "al": "Arik Air", "to": "Lagos", "Flights": 0}, {"fp": "COO", "from": "Cotonou", "ap": "LOS", "country": "Nigeria", "al": "Arik Air", "to": "Total", "Flights": 0}, {"fp": "COO", "from": "Cotonou", "ap": "DLA", "country": "Cameroon", "al": "Karinou Airlines", "to": "Douala", "Flights": 1.0}, {"fp": "COO", "from": "Cotonou", "ap": "DLA", "country": "Cameroon", "al": "Total", "to": "Douala", "Flights": 0}, {"fp": "COO", "from": "Cotonou", "ap": "Total", "country": "Cameroon", "al": "Karinou Airlines", "to": "Douala", "Flights": 0}, {"fp": "COO", "from": "Cotonou", "ap": "DLA", "country": "Total", "al": "Karinou Airlines", "to": "Douala", "Flights": 0}, {"fp": "COO", "from": "Total", "ap": "DLA", "country": "Cameroon", "al": "Karinou Airlines", "to": "Douala", "Flights": 0}, {"fp": "Total", "from": "Cotonou", "ap": "DLA", "country": "Cameroon", "al": "Karinou Airlines", "to": "Douala", "Flights": 0}, {"fp": "COO", "from": "Cotonou", "ap": "DLA", "country": "Cameroon", "al": "Karinou Airlines", "to": "Total", "Flights": 0}, {"fp": "COO", "from": "Cotonou", "ap": "DLA", "country": "Cameroon", "al": "Flex Flight", "to": "Douala", "Flights": 2.0}, {"fp": "COO", "from": "Cotonou", "ap": "DLA", "country": "Cameroon", "al": "Total", "to": "Douala", "Flights": 0}, {"fp": "COO", "from": "Cotonou", "ap": "Total", "country": "Cameroon", "al": "Flex Flight", "to": "Douala", "Flights": 0}, {"fp": "COO", "from": "Cotonou", "ap": "DLA", "country": "Total", "al": "Flex Flight", "to": "Douala", "Flights": 0}, {"fp": "COO", "from": "Total", "ap": "DLA", "country": "Cameroon", "al": "Flex Flight", "to": "Douala", "Flights": 0}, {"fp": "Total", "from": "Cotonou", "ap": "DLA", "country": "Cameroon", "al": "Flex Flight", "to": "Douala", "Flights": 0}, {"fp": "COO", "from": "Cotonou", "ap": "DLA", "country": "Cameroon", "al": "Flex Flight", "to": "Total", "Flights": 0}, {"fp": "COO", "from": "Cotonou", "ap": "DLA", "country": "Cameroon", "al": "Camair-Co", "to": "Douala", "Flights": 2.2}, {"fp": "COO", "from": "Cotonou", "ap": "DLA", "country": "Cameroon", "al": "Total", "to": "Douala", "Flights": 0}, {"fp": "COO", "from": "Cotonou", "ap": "Total", "country": "Cameroon", "al": "Camair-Co", "to": "Douala", "Flights": 0}, {"fp": "COO", "from": "Cotonou", "ap": "DLA", "country": "Total", "al": "Camair-Co", "to": "Douala", "Flights": 0}, {"fp": "COO", "from": "Total", "ap": "DLA", "country": "Cameroon", "al": "Camair-Co", "to": "Douala", "Flights": 0}, {"fp": "Total", "from": "Cotonou", "ap": "DLA", "country": "Cameroon", "al": "Camair-Co", "to": "Douala", "Flights": 0}, {"fp": "COO", "from": "Cotonou", "ap": "DLA", "country": "Cameroon", "al": "Camair-Co", "to": "Total", "Flights": 0}, {"fp": "COO", "from": "Cotonou", "ap": "DLA", "country": "Cameroon", "al": "Arik Air", "to": "Douala", "Flights": 5.8}, {"fp": "COO", "from": "Cotonou", "ap": "DLA", "country": "Cameroon", "al": "Total", "to": "Douala", "Flights": 0}, {"fp": "COO", "from": "Cotonou", "ap": "Total", "country": "Cameroon", "al": "Arik Air", "to": "Douala", "Flights": 0}, {"fp": "COO", "from": "Cotonou", "ap": "DLA", "country": "Total", "al": "Arik Air", "to": "Douala", "Flights": 0}, {"fp": "COO", "from": "Total", "ap": "DLA", "country": "Cameroon", "al": "Arik Air", "to": "Douala", "Flights": 0}, {"fp": "Total", "from": "Cotonou", "ap": "DLA", "country": "Cameroon", "al": "Arik Air", "to": "Douala", "Flights": 0}, {"fp": "COO", "from": "Cotonou", "ap": "DLA", "country": "Cameroon", "al": "Arik Air", "to": "Total", "Flights": 0}, {"fp": "COO", "from": "Cotonou", "ap": "DLA", "country": "Cameroon", "al": "Trans Air Congo", "to": "Douala", "Flights": 2.0}, {"fp": "COO", "from": "Cotonou", "ap": "DLA", "country": "Cameroon", "al": "Total", "to": "Douala", "Flights": 0}, {"fp": "COO", "from": "Cotonou", "ap": "Total", "country": "Cameroon", "al": "Trans Air Congo", "to": "Douala", "Flights": 0}, {"fp": "COO", "from": "Cotonou", "ap": "DLA", "country": "Total", "al": "Trans Air Congo", "to": "Douala", "Flights": 0}, {"fp": "COO", "from": "Total", "ap": "DLA", "country": "Cameroon", "al": "Trans Air Congo", "to": "Douala", "Flights": 0}, {"fp": "Total", "from": "Cotonou", "ap": "DLA", "country": "Cameroon", "al": "Trans Air Congo", "to": "Douala", "Flights": 0}, {"fp": "COO", "from": "Cotonou", "ap": "DLA", "country": "Cameroon", "al": "Trans Air Congo", "to": "Total", "Flights": 0}, {"fp": "COO", "from": "Cotonou", "ap": "ADD", "country": "Ethiopia", "al": "Ethiopian Airlines", "to": "Addis Ababa", "Flights": 3.0}, {"fp": "COO", "from": "Cotonou", "ap": "ADD", "country": "Ethiopia", "al": "Total", "to": "Addis Ababa", "Flights": 0}, {"fp": "COO", "from": "Cotonou", "ap": "Total", "country": "Ethiopia", "al": "Ethiopian Airlines", "to": "Addis Ababa", "Flights": 0}, {"fp": "COO", "from": "Cotonou", "ap": "ADD", "country": "Total", "al": "Ethiopian Airlines", "to": "Addis Ababa", "Flights": 0}, {"fp": "COO", "from": "Total", "ap": "ADD", "country": "Ethiopia", "al": "Ethiopian Airlines", "to": "Addis Ababa", "Flights": 0}, {"fp": "Total", "from": "Cotonou", "ap": "ADD", "country": "Ethiopia", "al": "Ethiopian Airlines", "to": "Addis Ababa", "Flights": 0}, {"fp": "COO", "from": "Cotonou", "ap": "ADD", "country": "Ethiopia", "al": "Ethiopian Airlines", "to": "Total", "Flights": 0}, {"fp": "COO", "from": "Cotonou", "ap": "IST", "country": "Turkey", "al": "Turkish Airlines", "to": "Istanbul", "Flights": 2.0}, {"fp": "COO", "from": "Cotonou", "ap": "IST", "country": "Turkey", "al": "Total", "to": "Istanbul", "Flights": 0}, {"fp": "COO", "from": "Cotonou", "ap": "Total", "country": "Turkey", "al": "Turkish Airlines", "to": "Istanbul", "Flights": 0}, {"fp": "COO", "from": "Cotonou", "ap": "IST", "country": "Total", "al": "Turkish Airlines", "to": "Istanbul", "Flights": 0}, {"fp": "COO", "from": "Total", "ap": "IST", "country": "Turkey", "al": "Turkish Airlines", "to": "Istanbul", "Flights": 0}, {"fp": "Total", "from": "Cotonou", "ap": "IST", "country": "Turkey", "al": "Turkish Airlines", "to": "Istanbul", "Flights": 0}, {"fp": "COO", "from": "Cotonou", "ap": "IST", "country": "Turkey", "al": "Turkish Airlines", "to": "Total", "Flights": 0}, {"fp": "COO", "from": "Cotonou", "ap": "SSG", "country": "Equatorial Guinea", "al": "Ceiba Intercontinental", "to": "Malabo", "Flights": 1.5}, {"fp": "COO", "from": "Cotonou", "ap": "SSG", "country": "Equatorial Guinea", "al": "Total", "to": "Malabo", "Flights": 0}, {"fp": "COO", "from": "Cotonou", "ap": "Total", "country": "Equatorial Guinea", "al": "Ceiba Intercontinental", "to": "Malabo", "Flights": 0}, {"fp": "COO", "from": "Cotonou", "ap": "SSG", "country": "Total", "al": "Ceiba Intercontinental", "to": "Malabo", "Flights": 0}, {"fp": "COO", "from": "Total", "ap": "SSG", "country": "Equatorial Guinea", "al": "Ceiba Intercontinental", "to": "Malabo", "Flights": 0}, {"fp": "Total", "from": "Cotonou", "ap": "SSG", "country": "Equatorial Guinea", "al": "Ceiba Intercontinental", "to": "Malabo", "Flights": 0}, {"fp": "COO", "from": "Cotonou", "ap": "SSG", "country": "Equatorial Guinea", "al": "Ceiba Intercontinental", "to": "Total", "Flights": 0}, {"fp": "COO", "from": "Cotonou", "ap": "CDG", "country": "France", "al": "Air France", "to": "Paris", "Flights": 5.0}, {"fp": "COO", "from": "Cotonou", "ap": "CDG", "country": "France", "al": "Total", "to": "Paris", "Flights": 0}, {"fp": "COO", "from": "Cotonou", "ap": "Total", "country": "France", "al": "Air France", "to": "Paris", "Flights": 0}, {"fp": "COO", "from": "Cotonou", "ap": "CDG", "country": "Total", "al": "Air France", "to": "Paris", "Flights": 0}, {"fp": "COO", "from": "Total", "ap": "CDG", "country": "France", "al": "Air France", "to": "Paris", "Flights": 0}, {"fp": "Total", "from": "Cotonou", "ap": "CDG", "country": "France", "al": "Air France", "to": "Paris", "Flights": 0}, {"fp": "COO", "from": "Cotonou", "ap": "CDG", "country": "France", "al": "Air France", "to": "Total", "Flights": 0}, {"fp": "COO", "from": "Cotonou", "ap": "BZV", "country": "Congo", "al": "Wings of Lebanon", "to": "Brazzaville", "Flights": 0.8}, {"fp": "COO", "from": "Cotonou", "ap": "BZV", "country": "Congo", "al": "Total", "to": "Brazzaville", "Flights": 0}, {"fp": "COO", "from": "Cotonou", "ap": "Total", "country": "Congo", "al": "Wings of Lebanon", "to": "Brazzaville", "Flights": 0}, {"fp": "COO", "from": "Cotonou", "ap": "BZV", "country": "Total", "al": "Wings of Lebanon", "to": "Brazzaville", "Flights": 0}, {"fp": "COO", "from": "Total", "ap": "BZV", "country": "Congo", "al": "Wings of Lebanon", "to": "Brazzaville", "Flights": 0}, {"fp": "Total", "from": "Cotonou", "ap": "BZV", "country": "Congo", "al": "Wings of Lebanon", "to": "Brazzaville", "Flights": 0}, {"fp": "COO", "from": "Cotonou", "ap": "BZV", "country": "Congo", "al": "Wings of Lebanon", "to": "Total", "Flights": 0}, {"fp": "COO", "from": "Cotonou", "ap": "BZV", "country": "Congo", "al": "Trans Air Congo", "to": "Brazzaville", "Flights": 0.8}, {"fp": "COO", "from": "Cotonou", "ap": "BZV", "country": "Congo", "al": "Total", "to": "Brazzaville", "Flights": 0}, {"fp": "COO", "from": "Cotonou", "ap": "Total", "country": "Congo", "al": "Trans Air Congo", "to": "Brazzaville", "Flights": 0}, {"fp": "COO", "from": "Cotonou", "ap": "BZV", "country": "Total", "al": "Trans Air Congo", "to": "Brazzaville", "Flights": 0}, {"fp": "COO", "from": "Total", "ap": "BZV", "country": "Congo", "al": "Trans Air Congo", "to": "Brazzaville", "Flights": 0}, {"fp": "Total", "from": "Cotonou", "ap": "BZV", "country": "Congo", "al": "Trans Air Congo", "to": "Brazzaville", "Flights": 0}, {"fp": "COO", "from": "Cotonou", "ap": "BZV", "country": "Congo", "al": "Trans Air Congo", "to": "Total", "Flights": 0}, {"fp": "COO", "from": "Cotonou", "ap": "CMN", "country": "Morocco", "al": "Royal Air Maroc", "to": "Casablanca", "Flights": 2.2}, {"fp": "COO", "from": "Cotonou", "ap": "CMN", "country": "Morocco", "al": "Total", "to": "Casablanca", "Flights": 0}, {"fp": "COO", "from": "Cotonou", "ap": "Total", "country": "Morocco", "al": "Royal Air Maroc", "to": "Casablanca", "Flights": 0}, {"fp": "COO", "from": "Cotonou", "ap": "CMN", "country": "Total", "al": "Royal Air Maroc", "to": "Casablanca", "Flights": 0}, {"fp": "COO", "from": "Total", "ap": "CMN", "country": "Morocco", "al": "Royal Air Maroc", "to": "Casablanca", "Flights": 0}, {"fp": "Total", "from": "Cotonou", "ap": "CMN", "country": "Morocco", "al": "Royal Air Maroc", "to": "Casablanca", "Flights": 0}, {"fp": "COO", "from": "Cotonou", "ap": "CMN", "country": "Morocco", "al": "Royal Air Maroc", "to": "Total", "Flights": 0}, {"fp": "COO", "from": "Cotonou", "ap": "NSI", "country": "Cameroon", "al": "Camair-Co", "to": "Yaounde", "Flights": 0.5}, {"fp": "COO", "from": "Cotonou", "ap": "NSI", "country": "Cameroon", "al": "Total", "to": "Yaounde", "Flights": 0}, {"fp": "COO", "from": "Cotonou", "ap": "Total", "country": "Cameroon", "al": "Camair-Co", "to": "Yaounde", "Flights": 0}, {"fp": "COO", "from": "Cotonou", "ap": "NSI", "country": "Total", "al": "Camair-Co", "to": "Yaounde", "Flights": 0}, {"fp": "COO", "from": "Total", "ap": "NSI", "country": "Cameroon", "al": "Camair-Co", "to": "Yaounde", "Flights": 0}, {"fp": "Total", "from": "Cotonou", "ap": "NSI", "country": "Cameroon", "al": "Camair-Co", "to": "Yaounde", "Flights": 0}, {"fp": "COO", "from": "Cotonou", "ap": "NSI", "country": "Cameroon", "al": "Camair-Co", "to": "Total", "Flights": 0}, {"fp": "COO", "from": "Cotonou", "ap": "DKR", "country": "Senegal", "al": "Ceiba Intercontinental", "to": "Dakar", "Flights": 2.0}, {"fp": "COO", "from": "Cotonou", "ap": "DKR", "country": "Senegal", "al": "Total", "to": "Dakar", "Flights": 0}, {"fp": "COO", "from": "Cotonou", "ap": "Total", "country": "Senegal", "al": "Ceiba Intercontinental", "to": "Dakar", "Flights": 0}, {"fp": "COO", "from": "Cotonou", "ap": "DKR", "country": "Total", "al": "Ceiba Intercontinental", "to": "Dakar", "Flights": 0}, {"fp": "COO", "from": "Total", "ap": "DKR", "country": "Senegal", "al": "Ceiba Intercontinental", "to": "Dakar", "Flights": 0}, {"fp": "Total", "from": "Cotonou", "ap": "DKR", "country": "Senegal", "al": "Ceiba Intercontinental", "to": "Dakar", "Flights": 0}, {"fp": "COO", "from": "Cotonou", "ap": "DKR", "country": "Senegal", "al": "Ceiba Intercontinental", "to": "Total", "Flights": 0}, {"fp": "COO", "from": "Cotonou", "ap": "PNR", "country": "Congo", "al": "Trans Air Congo", "to": "Pointe Noire", "Flights": 0.5}, {"fp": "COO", "from": "Cotonou", "ap": "PNR", "country": "Congo", "al": "Total", "to": "Pointe Noire", "Flights": 0}, {"fp": "COO", "from": "Cotonou", "ap": "Total", "country": "Congo", "al": "Trans Air Congo", "to": "Pointe Noire", "Flights": 0}, {"fp": "COO", "from": "Cotonou", "ap": "PNR", "country": "Total", "al": "Trans Air Congo", "to": "Pointe Noire", "Flights": 0}, {"fp": "COO", "from": "Total", "ap": "PNR", "country": "Congo", "al": "Trans Air Congo", "to": "Pointe Noire", "Flights": 0}, {"fp": "Total", "from": "Cotonou", "ap": "PNR", "country": "Congo", "al": "Trans Air Congo", "to": "Pointe Noire", "Flights": 0}, {"fp": "COO", "from": "Cotonou", "ap": "PNR", "country": "Congo", "al": "Trans Air Congo", "to": "Total", "Flights": 0}, {"fp": "COO", "from": "Cotonou", "ap": "NBO", "country": "Kenya", "al": "Kenya Airways", "to": "Nairobi", "Flights": 1.5}, {"fp": "COO", "from": "Cotonou", "ap": "NBO", "country": "Kenya", "al": "Total", "to": "Nairobi", "Flights": 0}, {"fp": "COO", "from": "Cotonou", "ap": "Total", "country": "Kenya", "al": "Kenya Airways", "to": "Nairobi", "Flights": 0}, {"fp": "COO", "from": "Cotonou", "ap": "NBO", "country": "Total", "al": "Kenya Airways", "to": "Nairobi", "Flights": 0}, {"fp": "COO", "from": "Total", "ap": "NBO", "country": "Kenya", "al": "Kenya Airways", "to": "Nairobi", "Flights": 0}, {"fp": "Total", "from": "Cotonou", "ap": "NBO", "country": "Kenya", "al": "Kenya Airways", "to": "Nairobi", "Flights": 0}, {"fp": "COO", "from": "Cotonou", "ap": "NBO", "country": "Kenya", "al": "Kenya Airways", "to": "Total", "Flights": 0}, {"fp": "COO", "from": "Cotonou", "ap": "PHC", "country": "Nigeria", "al": "Air France", "to": "Port Harcourt", "Flights": 2.0}, {"fp": "COO", "from": "Cotonou", "ap": "PHC", "country": "Nigeria", "al": "Total", "to": "Port Harcourt", "Flights": 0}, {"fp": "COO", "from": "Cotonou", "ap": "Total", "country": "Nigeria", "al": "Air France", "to": "Port Harcourt", "Flights": 0}, {"fp": "COO", "from": "Cotonou", "ap": "PHC", "country": "Total", "al": "Air France", "to": "Port Harcourt", "Flights": 0}, {"fp": "COO", "from": "Total", "ap": "PHC", "country": "Nigeria", "al": "Air France", "to": "Port Harcourt", "Flights": 0}, {"fp": "Total", "from": "Cotonou", "ap": "PHC", "country": "Nigeria", "al": "Air France", "to": "Port Harcourt", "Flights": 0}, {"fp": "COO", "from": "Cotonou", "ap": "PHC", "country": "Nigeria", "al": "Air France", "to": "Total", "Flights": 0}, {"fp": "COO", "from": "Cotonou", "ap": "OUA", "country": "Burkina Faso", "al": "Air Burkina", "to": "Ouagadougou", "Flights": 2.5}, {"fp": "COO", "from": "Cotonou", "ap": "OUA", "country": "Burkina Faso", "al": "Total", "to": "Ouagadougou", "Flights": 0}, {"fp": "COO", "from": "Cotonou", "ap": "Total", "country": "Burkina Faso", "al": "Air Burkina", "to": "Ouagadougou", "Flights": 0}, {"fp": "COO", "from": "Cotonou", "ap": "OUA", "country": "Total", "al": "Air Burkina", "to": "Ouagadougou", "Flights": 0}, {"fp": "COO", "from": "Total", "ap": "OUA", "country": "Burkina Faso", "al": "Air Burkina", "to": "Ouagadougou", "Flights": 0}, {"fp": "Total", "from": "Cotonou", "ap": "OUA", "country": "Burkina Faso", "al": "Air Burkina", "to": "Ouagadougou", "Flights": 0}, {"fp": "COO", "from": "Cotonou", "ap": "OUA", "country": "Burkina Faso", "al": "Air Burkina", "to": "Total", "Flights": 0}, {"fp": "COO", "from": "Cotonou", "ap": "NDJ", "country": "Chad", "al": "ASKY", "to": "N'Djamena", "Flights": 2.0}, {"fp": "COO", "from": "Cotonou", "ap": "NDJ", "country": "Chad", "al": "Total", "to": "N'Djamena", "Flights": 0}, {"fp": "COO", "from": "Cotonou", "ap": "Total", "country": "Chad", "al": "ASKY", "to": "N'Djamena", "Flights": 0}, {"fp": "COO", "from": "Cotonou", "ap": "NDJ", "country": "Total", "al": "ASKY", "to": "N'Djamena", "Flights": 0}, {"fp": "COO", "from": "Total", "ap": "NDJ", "country": "Chad", "al": "ASKY", "to": "N'Djamena", "Flights": 0}, {"fp": "Total", "from": "Cotonou", "ap": "NDJ", "country": "Chad", "al": "ASKY", "to": "N'Djamena", "Flights": 0}, {"fp": "COO", "from": "Cotonou", "ap": "NDJ", "country": "Chad", "al": "ASKY", "to": "Total", "Flights": 0}, {"fp": "COO", "from": "Cotonou", "ap": "ABJ", "country": "Cote D'ivoire (Ivory Coast)", "al": "Brussels Airlines", "to": "Abidjan", "Flights": 3.0}, {"fp": "COO", "from": "Cotonou", "ap": "ABJ", "country": "Cote D'ivoire (Ivory Coast)", "al": "Total", "to": "Abidjan", "Flights": 0}, {"fp": "COO", "from": "Cotonou", "ap": "Total", "country": "Cote D'ivoire (Ivory Coast)", "al": "Brussels Airlines", "to": "Abidjan", "Flights": 0}, {"fp": "COO", "from": "Cotonou", "ap": "ABJ", "country": "Total", "al": "Brussels Airlines", "to": "Abidjan", "Flights": 0}, {"fp": "COO", "from": "Total", "ap": "ABJ", "country": "Cote D'ivoire (Ivory Coast)", "al": "Brussels Airlines", "to": "Abidjan", "Flights": 0}, {"fp": "Total", "from": "Cotonou", "ap": "ABJ", "country": "Cote D'ivoire (Ivory Coast)", "al": "Brussels Airlines", "to": "Abidjan", "Flights": 0}, {"fp": "COO", "from": "Cotonou", "ap": "ABJ", "country": "Cote D'ivoire (Ivory Coast)", "al": "Brussels Airlines", "to": "Total", "Flights": 0}, {"fp": "COO", "from": "Cotonou", "ap": "ABJ", "country": "Cote D'ivoire (Ivory Coast)", "al": "Air Cote d'Ivoire", "to": "Abidjan", "Flights": 14.8}, {"fp": "COO", "from": "Cotonou", "ap": "ABJ", "country": "Cote D'ivoire (Ivory Coast)", "al": "Total", "to": "Abidjan", "Flights": 0}, {"fp": "COO", "from": "Cotonou", "ap": "Total", "country": "Cote D'ivoire (Ivory Coast)", "al": "Air Cote d'Ivoire", "to": "Abidjan", "Flights": 0}, {"fp": "COO", "from": "Cotonou", "ap": "ABJ", "country": "Total", "al": "Air Cote d'Ivoire", "to": "Abidjan", "Flights": 0}, {"fp": "COO", "from": "Total", "ap": "ABJ", "country": "Cote D'ivoire (Ivory Coast)", "al": "Air Cote d'Ivoire", "to": "Abidjan", "Flights": 0}, {"fp": "Total", "from": "Cotonou", "ap": "ABJ", "country": "Cote D'ivoire (Ivory Coast)", "al": "Air Cote d'Ivoire", "to": "Abidjan", "Flights": 0}, {"fp": "COO", "from": "Cotonou", "ap": "ABJ", "country": "Cote D'ivoire (Ivory Coast)", "al": "Air Cote d'Ivoire", "to": "Total", "Flights": 0}, {"fp": "COO", "from": "Cotonou", "ap": "ABJ", "country": "Cote D'ivoire (Ivory Coast)", "al": "Turkish Airlines", "to": "Abidjan", "Flights": 2.0}, {"fp": "COO", "from": "Cotonou", "ap": "ABJ", "country": "Cote D'ivoire (Ivory Coast)", "al": "Total", "to": "Abidjan", "Flights": 0}, {"fp": "COO", "from": "Cotonou", "ap": "Total", "country": "Cote D'ivoire (Ivory Coast)", "al": "Turkish Airlines", "to": "Abidjan", "Flights": 0}, {"fp": "COO", "from": "Cotonou", "ap": "ABJ", "country": "Total", "al": "Turkish Airlines", "to": "Abidjan", "Flights": 0}, {"fp": "COO", "from": "Total", "ap": "ABJ", "country": "Cote D'ivoire (Ivory Coast)", "al": "Turkish Airlines", "to": "Abidjan", "Flights": 0}, {"fp": "Total", "from": "Cotonou", "ap": "ABJ", "country": "Cote D'ivoire (Ivory Coast)", "al": "Turkish Airlines", "to": "Abidjan", "Flights": 0}, {"fp": "COO", "from": "Cotonou", "ap": "ABJ", "country": "Cote D'ivoire (Ivory Coast)", "al": "Turkish Airlines", "to": "Total", "Flights": 0}, {"fp": "COO", "from": "Cotonou", "ap": "ABJ", "country": "Cote D'ivoire (Ivory Coast)", "al": "Arik Air", "to": "Abidjan", "Flights": 5.2}, {"fp": "COO", "from": "Cotonou", "ap": "ABJ", "country": "Cote D'ivoire (Ivory Coast)", "al": "Total", "to": "Abidjan", "Flights": 0}, {"fp": "COO", "from": "Cotonou", "ap": "Total", "country": "Cote D'ivoire (Ivory Coast)", "al": "Arik Air", "to": "Abidjan", "Flights": 0}, {"fp": "COO", "from": "Cotonou", "ap": "ABJ", "country": "Total", "al": "Arik Air", "to": "Abidjan", "Flights": 0}, {"fp": "COO", "from": "Total", "ap": "ABJ", "country": "Cote D'ivoire (Ivory Coast)", "al": "Arik Air", "to": "Abidjan", "Flights": 0}, {"fp": "Total", "from": "Cotonou", "ap": "ABJ", "country": "Cote D'ivoire (Ivory Coast)", "al": "Arik Air", "to": "Abidjan", "Flights": 0}, {"fp": "COO", "from": "Cotonou", "ap": "ABJ", "country": "Cote D'ivoire (Ivory Coast)", "al": "Arik Air", "to": "Total", "Flights": 0}]