{"KRZ": {}, "BZV": {"Kinshasa": {"7freq": 10.0, "airports": {"FIH": {"7freq": 10.0, "airlines": {"Kenya Airways": {"7freq": 2.75}, "Ethiopian Airlines": {"7freq": 1.25}, "Camair-Co": {"7freq": 0.5}, "ASKY": {"7freq": 2.5}, "Air Cote d'Ivoire": {"7freq": 3.0}}}}}, "Pointe Noire": {"7freq": 60.0, "airports": {"PNR": {"7freq": 60.0, "airlines": {"Estafeta Carga Aerea": {"7freq": 4.25}, "Royal Air Maroc": {"7freq": 2.5}, "Mountain Air Cargo": {"7freq": 0.5}, "Air Cote d'Ivoire": {"7freq": 3.25}, "Trans Air Congo": {"7freq": 26.5}, "Wings of Lebanon": {"7freq": 8.5}, "Air France": {"7freq": 1.0}, "Ethiopian Airlines": {"7freq": 4.25}, "South African Airways": {"7freq": 1.5}}}}}, "Luanda": {"7freq": 4.0, "airports": {"LAD": {"7freq": 4.0, "airlines": {"Air Cote d'Ivoire": {"7freq": 2.0}, "TAAG Angola Airlines": {"7freq": 2.0}}}}}, "Casablanca": {"7freq": 2.5, "airports": {"CMN": {"7freq": 2.5, "airlines": {"Royal Air Maroc": {"7freq": 2.5}}}}}, "Kigali": {"7freq": 3.0, "airports": {"KGL": {"7freq": 3.0, "airlines": {"RwandAir": {"7freq": 3.0}}}}}, "Paris": {"7freq": 3.75, "airports": {"CDG": {"7freq": 3.75, "airlines": {"Air France": {"7freq": 3.75}}}}}, "Abidjan": {"7freq": 2.5, "airports": {"ABJ": {"7freq": 2.5, "airlines": {"Air Cote d'Ivoire": {"7freq": 2.5}}}}}, "Lagos": {"7freq": 0.5, "airports": {"LOS": {"7freq": 0.5, "airlines": {"Cargolux": {"7freq": 0.5}}}}}, "Malabo": {"7freq": 0.5, "airports": {"SSG": {"7freq": 0.5, "airlines": {"Mountain Air Cargo": {"7freq": 0.5}}}}}, "Johannesburg": {"7freq": 1.5, "airports": {"JNB": {"7freq": 1.5, "airlines": {"South African Airways": {"7freq": 1.5}}}}}, "Addis Ababa": {"7freq": 6.0, "airports": {"ADD": {"7freq": 6.0, "airlines": {"Ethiopian Airlines": {"7freq": 6.0}}}}}, "Libreville": {"7freq": 2.25, "airports": {"LBV": {"7freq": 2.25, "airlines": {"Air Cote d'Ivoire": {"7freq": 0.75}, "Trans Air Congo": {"7freq": 1.5}}}}}, "Cotonou": {"7freq": 1.5, "airports": {"COO": {"7freq": 1.5, "airlines": {"Wings of Lebanon": {"7freq": 0.75}, "Trans Air Congo": {"7freq": 0.75}}}}}, "Nairobi": {"7freq": 3.5, "airports": {"NBO": {"7freq": 3.5, "airlines": {"Kenya Airways": {"7freq": 2.75}, "Cargolux": {"7freq": 0.75}}}}}, "Douala": {"7freq": 5.0, "airports": {"DLA": {"7freq": 5.0, "airlines": {"RwandAir": {"7freq": 3.0}, "Trans Air Congo": {"7freq": 2.0}}}}}}, "BUX": {"Kinshasa": {"7freq": 0.5, "airports": {"FIH": {"7freq": 0.5, "airlines": {}}}}}, "GOM": {"Kinshasa": {"7freq": 7.0, "airports": {"FIH": {"7freq": 7.0, "airlines": {"flyCAA": {"7freq": 4.25}}}}}, "Bujumbura": {"7freq": 2.0, "airports": {"BJM": {"7freq": 2.0, "airlines": {"Ethiopian Airlines": {"7freq": 2.0}}}}}, "Addis Ababa": {"7freq": 2.5, "airports": {"ADD": {"7freq": 2.5, "airlines": {"Ethiopian Airlines": {"7freq": 2.5}}}}}}, "FKI": {"Kinshasa": {"7freq": 3.0, "airports": {"FIH": {"7freq": 3.0, "airlines": {"flyCAA": {"7freq": 0.75}}}}}}, "MJM": {"Kinshasa": {"7freq": 10.25, "airports": {"FIH": {"7freq": 10.25, "airlines": {"flyCAA": {"7freq": 7.25}}}}}, "Lubumbashi": {"7freq": 6.5, "airports": {"FBM": {"7freq": 6.5, "airlines": {"flyCAA": {"7freq": 5.5}}}}}}, "KEE": {}, "PNR": {"Addis Ababa": {"7freq": 4.25, "airports": {"ADD": {"7freq": 4.25, "airlines": {"Ethiopian Airlines": {"7freq": 4.25}}}}}, "Casablanca": {"7freq": 2.5, "airports": {"CMN": {"7freq": 2.5, "airlines": {"Royal Air Maroc": {"7freq": 2.5}}}}}, "Paris": {"7freq": 6.5, "airports": {"CDG": {"7freq": 6.5, "airlines": {"Air France": {"7freq": 6.5}}}}}, "Abidjan": {"7freq": 4.0, "airports": {"ABJ": {"7freq": 4.0, "airlines": {"Air Cote d'Ivoire": {"7freq": 4.0}}}}}, "Malabo": {"7freq": 0.5, "airports": {"SSG": {"7freq": 0.5, "airlines": {"Mountain Air Cargo": {"7freq": 0.5}}}}}, "Brazzaville": {"7freq": 60.0, "airports": {"BZV": {"7freq": 60.0, "airlines": {"Estafeta Carga Aerea": {"7freq": 4.25}, "Royal Air Maroc": {"7freq": 2.5}, "Mountain Air Cargo": {"7freq": 0.5}, "Air Cote d'Ivoire": {"7freq": 3.25}, "Trans Air Congo": {"7freq": 26.5}, "Wings of Lebanon": {"7freq": 8.5}, "Air France": {"7freq": 1.0}, "Ethiopian Airlines": {"7freq": 4.25}, "South African Airways": {"7freq": 1.5}}}}}, "Johannesburg": {"7freq": 1.5, "airports": {"JNB": {"7freq": 1.5, "airlines": {"South African Airways": {"7freq": 1.5}}}}}, "Liege": {"7freq": 0.5, "airports": {"LGG": {"7freq": 0.5, "airlines": {"Allied Air": {"7freq": 0.5}}}}}, "Libreville": {"7freq": 4.0, "airports": {"LBV": {"7freq": 4.0, "airlines": {"Air Cote d'Ivoire": {"7freq": 1.0}, "Trans Air Congo": {"7freq": 3.0}}}}}, "Cotonou": {"7freq": 0.5, "airports": {"COO": {"7freq": 0.5, "airlines": {"Trans Air Congo": {"7freq": 0.5}}}}}, "Douala": {"7freq": 1.5, "airports": {"DLA": {"7freq": 1.5, "airlines": {"Trans Air Congo": {"7freq": 1.5}}}}}, "Port Gentil": {"7freq": 5.5, "airports": {"POG": {"7freq": 5.5, "airlines": {"Afrijet Business Services": {"7freq": 2.0}, "Estafeta Carga Aerea": {"7freq": 1.0}}}}}}, "KMK": {"Mara Lodges": {"7freq": 1.25, "airports": {"MRE": {"7freq": 1.25, "airlines": {"Fly SAX": {"7freq": 1.25}}}}}, "Nairobi": {"7freq": 1.0, "airports": {"WIL": {"7freq": 1.0, "airlines": {"Fly SAX": {"7freq": 1.0}}}}}}, "MDK": {"Kinshasa": {"7freq": 2.25, "airports": {"FIH": {"7freq": 2.25, "airlines": {"flyCAA": {"7freq": 1.0}}}}}}, "KGA": {"Kinshasa": {"7freq": 2.5, "airports": {"FIH": {"7freq": 2.5, "airlines": {"flyCAA": {"7freq": 0.5}}}}}, "Lubumbashi": {"7freq": 1.0, "airports": {"FBM": {"7freq": 1.0, "airlines": {}}}}}, "LIQ": {"Kinshasa": {"7freq": 0.5, "airports": {"FIH": {"7freq": 0.5, "airlines": {"flyCAA": {"7freq": 0.5}}}}}}, "GMA": {"Kinshasa": {"7freq": 4.5, "airports": {"FIH": {"7freq": 4.5, "airlines": {"flyCAA": {"7freq": 2.5}}}}}}, "FMI": {"Lubumbashi": {"7freq": 4.0, "airports": {"FBM": {"7freq": 4.0, "airlines": {"flyCAA": {"7freq": 2.0}}}}}}, "FIH": {"Istanbul": {"7freq": 3.5, "airports": {"IST": {"7freq": 3.5, "airlines": {"Turkish Airlines": {"7freq": 3.5}}}}}, "Paris": {"7freq": 3.5, "airports": {"CDG": {"7freq": 3.5, "airlines": {"Air France": {"7freq": 3.5}}}}}, "Mbuji Mayi": {"7freq": 10.25, "airports": {"MJM": {"7freq": 10.25, "airlines": {"flyCAA": {"7freq": 7.25}}}}}, "Entebbe": {"7freq": 0.5, "airports": {"EBB": {"7freq": 0.5, "airlines": {"Turkish Airlines": {"7freq": 0.5}}}}}, "Brazzaville": {"7freq": 10.0, "airports": {"BZV": {"7freq": 10.0, "airlines": {"Kenya Airways": {"7freq": 2.75}, "Camair-Co": {"7freq": 0.5}, "Ethiopian Airlines": {"7freq": 1.25}, "Air Cote d'Ivoire": {"7freq": 3.0}, "ASKY": {"7freq": 2.5}}}}}, "Johannesburg": {"7freq": 7.0, "airports": {"JNB": {"7freq": 7.0, "airlines": {"South African Airways": {"7freq": 7.0}}}}}, "Kindu": {"7freq": 3.5, "airports": {"KND": {"7freq": 3.5, "airlines": {"flyCAA": {"7freq": 2.0}}}}}, "Luanda": {"7freq": 4.5, "airports": {"LAD": {"7freq": 4.5, "airlines": {"Brussels Airlines": {"7freq": 1.5}, "TAAG Angola Airlines": {"7freq": 2.0}, "Air France": {"7freq": 1.0}}}}}, "Mbandaka": {"7freq": 2.25, "airports": {"MDK": {"7freq": 2.25, "airlines": {"flyCAA": {"7freq": 1.0}}}}}, "Goma": {"7freq": 7.0, "airports": {"GOM": {"7freq": 7.0, "airlines": {"flyCAA": {"7freq": 4.25}}}}}, "Brussels": {"7freq": 4.5, "airports": {"BRU": {"7freq": 4.5, "airlines": {"Brussels Airlines": {"7freq": 4.5}}}}}, "Port Harcourt": {"7freq": 0.5, "airports": {"PHC": {"7freq": 0.5, "airlines": {"Cargolux": {"7freq": 0.5}}}}}, "Addis Ababa": {"7freq": 8.25, "airports": {"ADD": {"7freq": 8.25, "airlines": {"Ethiopian Airlines": {"7freq": 8.25}}}}}, "Lome": {"7freq": 3.0, "airports": {"LFW": {"7freq": 3.0, "airlines": {"ASKY": {"7freq": 2.5}, "Ethiopian Airlines": {"7freq": 0.5}}}}}, "Kisangani": {"7freq": 3.0, "airports": {"FKI": {"7freq": 3.0, "airlines": {"flyCAA": {"7freq": 0.75}}}}}, "Kananga": {"7freq": 2.5, "airports": {"KGA": {"7freq": 2.5, "airlines": {"flyCAA": {"7freq": 0.5}}}}}, "Bamako": {"7freq": 0.5, "airports": {"BKO": {"7freq": 0.5, "airlines": {"Cargolux": {"7freq": 0.5}}}}}, "Nairobi": {"7freq": 11.75, "airports": {"NBO": {"7freq": 11.75, "airlines": {"Taquan Air": {"7freq": 3.0}, "Kenya Airways": {"7freq": 7.5}, "Turkish Airlines": {"7freq": 0.5}, "Cargolux": {"7freq": 0.75}}}}}, "Bumbar": {"7freq": 0.5, "airports": {"BMB": {"7freq": 0.5, "airlines": {"flyCAA": {"7freq": 0.5}}}}}, "Libreville": {"7freq": 6.75, "airports": {"LBV": {"7freq": 6.75, "airlines": {"Ethiopian Airlines": {"7freq": 1.0}, "ASKY": {"7freq": 1.0}, "Air Cote d'Ivoire": {"7freq": 2.25}, "Turkish Airlines": {"7freq": 2.5}}}}}, "Casablanca": {"7freq": 3.0, "airports": {"CMN": {"7freq": 3.0, "airlines": {"Royal Air Maroc": {"7freq": 3.0}}}}}, "Abidjan": {"7freq": 3.0, "airports": {"ABJ": {"7freq": 3.0, "airlines": {"Air Cote d'Ivoire": {"7freq": 3.0}}}}}, "Gemena": {"7freq": 4.5, "airports": {"GMA": {"7freq": 4.5, "airlines": {"flyCAA": {"7freq": 2.5}}}}}, "Congo": {"7freq": 1.0, "airports": {"BUX": {"7freq": 0.5, "airlines": {}}, "LIQ": {"7freq": 0.5, "airlines": {"flyCAA": {"7freq": 0.5}}}}}, "Lubumbashi": {"7freq": 7.0, "airports": {"FBM": {"7freq": 7.0, "airlines": {"flyCAA": {"7freq": 1.25}}}}}, "Douala": {"7freq": 1.5, "airports": {"DLA": {"7freq": 1.5, "airlines": {"Camair-Co": {"7freq": 0.5}, "Brussels Airlines": {"7freq": 1.0}}}}}}, "KND": {"Kinshasa": {"7freq": 3.5, "airports": {"FIH": {"7freq": 3.5, "airlines": {"flyCAA": {"7freq": 2.0}}}}}}, "FBM": {"Kinshasa": {"7freq": 7.0, "airports": {"FIH": {"7freq": 7.0, "airlines": {"flyCAA": {"7freq": 1.25}}}}}, "Algiers": {"7freq": 0.5, "airports": {"ALG": {"7freq": 0.5, "airlines": {"Air Algerie": {"7freq": 0.5}}}}}, "Addis Ababa": {"7freq": 3.5, "airports": {"ADD": {"7freq": 3.5, "airlines": {"Ethiopian Airlines": {"7freq": 3.5}}}}}, "Djanet": {"7freq": 1.0, "airports": {"DJG": {"7freq": 1.0, "airlines": {"Air Algerie": {"7freq": 1.0}}}}}, "Mbuji Mayi": {"7freq": 6.5, "airports": {"MJM": {"7freq": 6.5, "airlines": {"flyCAA": {"7freq": 5.5}}}}}, "Ndola": {"7freq": 7.0, "airports": {"NLA": {"7freq": 7.0, "airlines": {"Kenya Airways": {"7freq": 3.5}, "Ethiopian Airlines": {"7freq": 3.5}}}}}, "Johannesburg": {"7freq": 6.0, "airports": {"JNB": {"7freq": 6.0, "airlines": {"South African Airways": {"7freq": 6.0}}}}}, "Congo": {"7freq": 4.0, "airports": {"FMI": {"7freq": 4.0, "airlines": {"flyCAA": {"7freq": 2.0}}}}}, "Kananga": {"7freq": 1.0, "airports": {"KGA": {"7freq": 1.0, "airlines": {}}}}, "Nairobi": {"7freq": 3.75, "airports": {"NBO": {"7freq": 3.75, "airlines": {"Kenya Airways": {"7freq": 3.75}}}}}}}