{"Goma(-1.67081, 29.2385)": {"count": 2.0, "country": "Congo", "BJM": {"count": 2.0, "airports": {"GOM": {"7freq": 2.0, "airlines": {"Ethiopian Airlines": {"7freq": 2.0}}}}}, "coords": [-1.67081, 29.2385]}, "Juba(4.87201, 31.6011)": {"count": 0.5, "country": "South Sudan", "BJM": {"count": 0.5, "airports": {"JUB": {"7freq": 0.5, "airlines": {"Ethiopian Airlines": {"7freq": 0.5}}}}}, "coords": [4.87201, 31.6011]}, "Brussels(50.46, 4.45278)": {"count": 0.5, "country": "Belgium", "BJM": {"count": 0.5, "airports": {"BRU": {"7freq": 0.5, "airlines": {"Brussels Airlines": {"7freq": 0.5}}}}}, "coords": [50.46, 4.45278]}, "Addis Ababa(8.9800689, 38.7989319)": {"count": 3.5, "country": "Ethiopia", "BJM": {"count": 3.5, "airports": {"ADD": {"7freq": 3.5, "airlines": {"Ethiopian Airlines": {"7freq": 3.5}}}}}, "coords": [8.9800689, 38.7989319]}, "Kigali(-1.96862, 30.1395)": {"count": 23.75, "country": "Rwanda", "BJM": {"count": 23.75, "airports": {"KGL": {"7freq": 23.75, "airlines": {"RwandAir": {"7freq": 7.0}, "Kenya Airways": {"7freq": 11.25}, "Ethiopian Airlines": {"7freq": 5.0}, "Brussels Airlines": {"7freq": 0.5}}}}}, "coords": [-1.96862, 30.1395]}, "Nairobi(-1.321111, 36.814722)": {"count": 11.25, "country": "Kenya", "BJM": {"count": 11.25, "airports": {"NBO": {"7freq": 11.25, "airlines": {"Kenya Airways": {"7freq": 11.25}}}}}, "coords": [-1.321111, 36.814722]}}